uniconnector/__init__.py
uniconnector/connector.py
uniconnector-0.1.0.dist-info/METADATA
uniconnector-0.1.0.dist-info/WHEEL
uniconnector-0.1.0.dist-info/top_level.txt
uniconnector-0.1.0.dist-info/RECORD
